mvg/__init__.py
mvg/mvgapi.py
mvgext-1.0.3.dist-info/LICENSE
mvgext-1.0.3.dist-info/METADATA
mvgext-1.0.3.dist-info/WHEEL
mvgext-1.0.3.dist-info/top_level.txt
mvgext-1.0.3.dist-info/RECORD
