Metadata-Version: 2.1
Name: mvgext
Version: 1.0.3
Summary: An unofficial interface to timetable information of the Münchner Verkehrsgesellschaft (MVG).
Author-email: Andreas Haagner <ahaagner@gmx.de>
Project-URL: Documentation, https://github.com/piehler73/mvgext
Project-URL: Source, https://github.com/piehler73/mvgext
Project-URL: Bug Tracker, https://github.com/piehler73/mvgext/issues
Classifier: License :: OSI Approved :: MIT License
Classifier: Operating System :: OS Independent
Classifier: Programming Language :: Python :: 3
Requires-Python: >=3.7
License-File: LICENSE
Requires-Dist: aiohttp (~=3.8)
Requires-Dist: furl (~=2.1)
Provides-Extra: dev
Requires-Dist: autopep8 ; extra == 'dev'
Requires-Dist: build ; extra == 'dev'
Requires-Dist: flake8 ; extra == 'dev'
Requires-Dist: mypy ; extra == 'dev'
Requires-Dist: pylint ; extra == 'dev'
Requires-Dist: pytest ; extra == 'dev'
Requires-Dist: pytest-asyncio ; extra == 'dev'
Requires-Dist: sphinx ; extra == 'dev'
Requires-Dist: sphinx-mdinclude ; extra == 'dev'
Requires-Dist: sphinx-pyproject ; extra == 'dev'
Requires-Dist: sphinx-rtd-theme ; extra == 'dev'
Requires-Dist: twine ; extra == 'dev'
